<?xml version="1.0" encoding="UTF-8"?>
<prefab>
  <property name="CopyAirBlocks" value="True" />
  <property name="AllowTopSoilDecorations" value="True" />
  <property name="TraderArea" value="False" />
  <property name="ExcludeDistantPOIMesh" value="False" />
  <property name="ExcludePOICulling" value="False" />
  <property name="DifficultyTier" value="1" />
  <property name="RotationToFaceNorth" value="2" />
  <property name="YOffset" value="-1" />
  <property name="DistantPOIYOffset" value="0" />
  <property name="EditorGroups" value="rural" />
  <property name="ShowQuestClearCount" value="1" />
  <property name="Zoning" value="Rural, ResidentialOld" />
  <property name="AllowedBiomes" value="pine_forest,desert" />
  <property name="AllowedTownships" value="rural" />
  <property name="Tags" value="megacity,cpmegarural" />
  <property name="PrefabSize" value="100, 22, 100" />
  <property name="POIMarkerSize" value="44, 13, 3#44, 13, 3" />
  <property name="POIMarkerStart" value="0, 0, -3#56, 0, -3" />
  <property name="POIMarkerGroup" value="1,2" />
  <property name="POIMarkerTags" value="#" />
  <property name="POIMarkerType" value="PartSpawn,PartSpawn" />
  <property name="POIMarkerPartToSpawn" value="part_driveway_rural_11,part_driveway_rural_11" />
  <property name="POIMarkerPartRotations" value="2,2" />
  <property name="POIMarkerPartSpawnChance" value="1,1" />
  <property class="IndexedBlockOffsets">
    <property class="POILight">
      <property name="0" value="50, 8, 66" />
      <property name="1" value="53, 6, 66" />
      <property name="2" value="55, 8, 66" />
      <property name="3" value="59, 8, 66" />
      <property name="4" value="61, 6, 66" />
      <property name="5" value="55, 4, 67" />
      <property name="6" value="59, 4, 67" />
      <property name="7" value="51, 8, 71" />
      <property name="8" value="56, 8, 71" />
      <property name="9" value="58, 8, 71" />
    </property>
    <property class="TraderOnOff">
      <property name="0" value="51, 3, 42" />
    </property>
    <property class="quest_feather">
      <property name="0" value="67, 1, 97" />
    </property>
  </property>
  <property class="Stats">
    <property name="TotalVertices" value="916964" />
    <property name="TotalTriangles" value="913352" />
    <property class="BlockEntities">
      <property name="Vertices" value="757266" />
      <property name="Triangles" value="797530" />
    </property>
    <property class="ChunkMeshes0">
      <property name="Vertices" value="129066" />
      <property name="Triangles" value="71362" />
    </property>
    <property class="ChunkMeshes1">
      <property name="Vertices" value="0" />
      <property name="Triangles" value="0" />
    </property>
    <property class="ChunkMeshes2">
      <property name="Vertices" value="1584" />
      <property name="Triangles" value="792" />
    </property>
    <property class="ChunkMeshes3">
      <property name="Vertices" value="0" />
      <property name="Triangles" value="0" />
    </property>
    <property class="ChunkMeshes4">
      <property name="Vertices" value="3268" />
      <property name="Triangles" value="3184" />
    </property>
    <property class="ChunkMeshes5">
      <property name="Vertices" value="0" />
      <property name="Triangles" value="0" />
    </property>
    <property class="ChunkMeshes6">
      <property name="Vertices" value="0" />
      <property name="Triangles" value="0" />
    </property>
    <property class="ChunkMeshes7">
      <property name="Vertices" value="25780" />
      <property name="Triangles" value="40484" />
    </property>
    <property class="ChunkMeshes8">
      <property name="Vertices" value="0" />
      <property name="Triangles" value="0" />
    </property>
    <property class="ChunkMeshes9">
      <property name="Vertices" value="0" />
      <property name="Triangles" value="0" />
    </property>
  </property>
</prefab>