<?xml version="1.0" encoding="UTF-8"?>
<prefab>
  <property name="CopyAirBlocks" value="True" />
  <property name="AllowTopSoilDecorations" value="True" />
  <property name="TraderArea" value="False" />
  <property name="ExcludeDistantPOIMesh" value="False" />
  <property name="ExcludePOICulling" value="False" />
  <property name="QuestTags" value="clear,fetch" />
  <property name="DifficultyTier" value="1" />
  <property name="Zoning" value="Industrial" />
  <property name="AllowedBiomes" value="pine_forest" />
  <property name="AllowedTownships" value="city,town" />
  <property name="RotationToFaceNorth" value="3" />
  <property name="YOffset" value="-1" />
  <property name="DistantPOIYOffset" value="0" />
  <property name="EditorGroups" value="industrial" />
  <property name="SleeperVolumeStart" value="7, 1, 14#6, 6, 10#1, 1, 0" />
  <property name="SleeperVolumeSize" value="26, 4, 18#27, 5, 22#41, 3, 42" />
  <property name="SleeperVolumeGroup" value="S_-Group_Generic_Zombie,4,4,S_Zom_Utility_Worker,2,2,S_-Group_Generic_Zombie,7,9" />
  <property name="SleeperVolumeGameStageAdjust" value="," />
  <property name="SleeperIsLootVolume" value="True,False,False" />
  <property name="SleeperIsQuestExclude" value="False,False,False" />
  <property name="SleeperVolumeFlags" value="0,0,0" />
  <property name="SleeperVolumeGroupId" value="0,0,0" />
  <property name="ShowQuestClearCount" value="1" />
  <property name="Tags" value="snow,desert,industrial,pine_forest" />
  <property name="PrefabSize" value="42, 14, 42" />
  <property name="POIMarkerSize" value="1, 13, 8" />
  <property name="POIMarkerStart" value="-1, 0, 17" />
  <property name="POIMarkerGroup" value="1" />
  <property name="POIMarkerTags" value="" />
  <property name="POIMarkerType" value="PartSpawn" />
  <property name="POIMarkerPartToSpawn" value="part_driveway_industrial_10" />
  <property name="POIMarkerPartRotations" value="3" />
  <property name="POIMarkerPartSpawnChance" value="1" />
  <property class="IndexedBlockOffsets">
    <property class="Rally">
      <property name="0" value="0, 1, 23" />
    </property>
    <property class="FetchContainer">
      <property name="0" value="31, 3, 27" />
    </property>
    <property class="POILight">
      <property name="0" value="31, 9, 26" />
    </property>
  </property>
  <property class="Stats">
    <property name="TotalVertices" value="406459" />
    <property name="TotalTriangles" value="382747" />
    <property class="BlockEntities">
      <property name="Vertices" value="315488" />
      <property name="Triangles" value="321688" />
    </property>
    <property class="ChunkMeshes0">
      <property name="Vertices" value="84271" />
      <property name="Triangles" value="52301" />
    </property>
    <property class="ChunkMeshes1">
      <property name="Vertices" value="0" />
      <property name="Triangles" value="0" />
    </property>
    <property class="ChunkMeshes2">
      <property name="Vertices" value="264" />
      <property name="Triangles" value="132" />
    </property>
    <property class="ChunkMeshes3">
      <property name="Vertices" value="0" />
      <property name="Triangles" value="0" />
    </property>
    <property class="ChunkMeshes4">
      <property name="Vertices" value="1764" />
      <property name="Triangles" value="1310" />
    </property>
    <property class="ChunkMeshes5">
      <property name="Vertices" value="0" />
      <property name="Triangles" value="0" />
    </property>
    <property class="ChunkMeshes6">
      <property name="Vertices" value="0" />
      <property name="Triangles" value="0" />
    </property>
    <property class="ChunkMeshes7">
      <property name="Vertices" value="4672" />
      <property name="Triangles" value="7316" />
    </property>
    <property class="ChunkMeshes8">
      <property name="Vertices" value="0" />
      <property name="Triangles" value="0" />
    </property>
    <property class="ChunkMeshes9">
      <property name="Vertices" value="0" />
      <property name="Triangles" value="0" />
    </property>
  </property>
</prefab>